xinput_gui/__init__.py
xinput_gui/__main__.py
xinput_gui/settings.py
xinput_gui/gui/__init__.py
xinput_gui/gui/dialog_about.py
xinput_gui/gui/dialog_create_master.py
xinput_gui/gui/dialog_device_info.py
xinput_gui/gui/dialog_edit.py
xinput_gui/gui/dialog_reattach.py
xinput_gui/gui/win_main.py
xinput_gui/gui/win_settings.py
xinput_gui/res/config.json
xinput_gui/res/xinput-gui.ui
xinput_gui/xinput/__init__.py
xinput_gui/xinput/devices.py
xinput_gui/xinput/xinput.py
xinput_gui-0.3.1.dist-info/LICENSE
xinput_gui-0.3.1.dist-info/METADATA
xinput_gui-0.3.1.dist-info/WHEEL
xinput_gui-0.3.1.dist-info/entry_points.txt
xinput_gui-0.3.1.dist-info/top_level.txt
xinput_gui-0.3.1.dist-info/RECORD
