Metadata-Version: 2.1
Name: xinput-gui
Version: 0.3.1
Summary: A simple GUI for Xorg's Xinput tool.
Home-page: https://github.com/IvanFon/xinput-gui
Author: Ivan Fonseca
Author-email: ivanfon@riseup.net
License: GPLv3+
Keywords: xinput keyboard mouse touchpad
Platform: UNKNOWN
Classifier: Development Status :: 4 - Beta
Classifier: Environment :: X11 Applications :: GTK
Classifier: Intended Audience :: End Users/Desktop
Classifier: License :: OSI Approved :: GNU General Public License v3 or later (GPLv3+)
Classifier: Natural Language :: English
Classifier: Operating System :: POSIX
Classifier: Programming Language :: Python :: 3 :: Only
Classifier: Programming Language :: Python :: 3.5
Classifier: Programming Language :: Python :: 3.6
Classifier: Programming Language :: Python :: 3.7
Classifier: Programming Language :: Python :: 3.8
Classifier: Topic :: Desktop Environment
Classifier: Topic :: Utilities
Requires-Dist: PyGObject
